<?xml version="1.0" encoding="UTF-8"?>
<!-- This is FICTITIOUS TEST DATA generated for the SWIM Developer project.
     Data model based on EUROCAE ED-254 (Arrival Sequence Service Performance Standard)
     and FIXM 4.3 (Flight Information Exchange Model).
     All validation credits belong to their respective owners (EUROCAE, FIXM CCB, EUROCONTROL).

     THIS FICTITIOUS DATA SET IS PROVIDED "AS IS" AND ANY EXPRESS OR IMPLIED WARRANTIES,
     INCLUDING, BUT NOT LIMITED TO, THE IMPLIED WARRANTIES OF MERCHANTABILITY AND FITNESS
     FOR A PARTICULAR PURPOSE ARE DISCLAIMED.

     Created by Marcelo Sales (marcelo.d.sales@gmail.com) for the SWIM Developer project.
     Project: https://github.com/orgs/swim-developer/repositories
     Purpose: Testing and validation of SWIM Extended AMAN (E-AMAN) services.
     All credits to the original specification authors must be preserved. -->
<arrivalSequence xmlns="http://www.fixm.aero/ed254/1.0"
                 xmlns:fb="http://www.fixm.aero/base/4.3"
                 xmlns:fx="http://www.fixm.aero/flight/4.3">
    <creationTime>2026-04-08T19:33:00Z</creationTime>
    <publicationTime>2026-04-08T19:33:01.000Z</publicationTime>
    <firstMessageAfterServiceOutage>false</firstMessageAfterServiceOutage>
    <aerodromeDesignator>LSZH</aerodromeDesignator>
    <sequenceEntries>
        <arrivalManagementInformation>
            <amanTargetLandingTime>2026-04-08T19:56:00Z</amanTargetLandingTime>
            <arrivalManagementHandlingIndicator>HAS_LANDED</arrivalManagementHandlingIndicator>
            <lastFiledRecord>false</lastFiledRecord>
            <sequenceNumber>1</sequenceNumber>
            <typeOfAircraft>A320</typeOfAircraft>
            <wakeTurbulenceIcaoCategory>L</wakeTurbulenceIcaoCategory>
            <assignedArrivalRunway>01L</assignedArrivalRunway>
            <flightIdentification>
                <arcid>DLH8366</arcid>
                <ades>LSZH</ades>
                <adep>LEMD</adep>
                <gufi codeSpace="urn:uuid"
                      creationTime="2026-04-08T14:33:00Z"
                      namespaceDomain="FULLY_QUALIFIED_DOMAIN_NAME"
                      namespaceIdentifier="provider.swim.aero">4475dd3f-b2f9-4753-ad30-3da81fed8d80</gufi>
            </flightIdentification>
        </arrivalManagementInformation>
        <arrivalManagementInformation>
            <amanTargetLandingTime>2026-04-08T20:01:00Z</amanTargetLandingTime>
            <arrivalManagementHandlingIndicator>SEQUENCED_FROZEN</arrivalManagementHandlingIndicator>
            <lastFiledRecord>false</lastFiledRecord>
            <sequenceNumber>2</sequenceNumber>
            <typeOfAircraft>A320</typeOfAircraft>
            <wakeTurbulenceIcaoCategory>M</wakeTurbulenceIcaoCategory>
            <assignedArrivalRunway>27L</assignedArrivalRunway>
            <meteringInformation>
                <amanTargetTimeOver>2026-04-08T19:47:00Z</amanTargetTimeOver>
                <delayAtPoint>PT8M29S</delayAtPoint>
                <planningStatus>CONTROLLED_TIME</planningStatus>
                <pointName>BOMBI</pointName>
                <pointUsage>FINAL_APPROACH_FIX</pointUsage>
            </meteringInformation>
            <flightIdentification>
                <arcid>BAW1535</arcid>
                <ades>LSZH</ades>
                <adep>LPPT</adep>
                <gufi codeSpace="urn:uuid"
                      creationTime="2026-04-08T07:33:00Z"
                      namespaceDomain="FULLY_QUALIFIED_DOMAIN_NAME"
                      namespaceIdentifier="provider.swim.aero">f6a19fda-c4d8-4811-9c05-7543ccbb87e5</gufi>
            </flightIdentification>
            <totalDelay>
                <arrivalDelay>526</arrivalDelay>
            </totalDelay>
        </arrivalManagementInformation>
        <arrivalManagementInformation>
            <amanTargetLandingTime>2026-04-08T20:02:00Z</amanTargetLandingTime>
            <arrivalManagementHandlingIndicator>SEQUENCED_STABLE</arrivalManagementHandlingIndicator>
            <lastFiledRecord>false</lastFiledRecord>
            <sequenceNumber>3</sequenceNumber>
            <typeOfAircraft>A320</typeOfAircraft>
            <wakeTurbulenceIcaoCategory>J</wakeTurbulenceIcaoCategory>
            <assignedArrivalRunway>27R</assignedArrivalRunway>
            <meteringInformation>
                <amanTargetTimeOver>2026-04-08T19:45:00Z</amanTargetTimeOver>
                <planningStatus>CONTROLLED_TIME</planningStatus>
                <pointName>GAVOS</pointName>
                <pointUsage>COORDINATION</pointUsage>
            </meteringInformation>
            <flightIdentification>
                <arcid>TAP3338</arcid>
                <ades>LSZH</ades>
                <adep>EIDW</adep>
                <gufi codeSpace="urn:uuid"
                      creationTime="2026-04-08T14:33:00Z"
                      namespaceDomain="FULLY_QUALIFIED_DOMAIN_NAME"
                      namespaceIdentifier="provider.swim.aero">a898cb89-e6f1-4e1a-a543-4475aefc611c</gufi>
            </flightIdentification>
        </arrivalManagementInformation>
        <arrivalManagementInformation>
            <amanTargetLandingTime>2026-04-08T20:09:00Z</amanTargetLandingTime>
            <arrivalManagementHandlingIndicator>DESEQUENCED</arrivalManagementHandlingIndicator>
            <lastFiledRecord>false</lastFiledRecord>
            <sequenceNumber>4</sequenceNumber>
            <typeOfAircraft>A388</typeOfAircraft>
            <wakeTurbulenceIcaoCategory>J</wakeTurbulenceIcaoCategory>
            <assignedArrivalRunway>25L</assignedArrivalRunway>
            <meteringInformation>
                <amanTargetTimeOver>2026-04-08T19:44:00Z</amanTargetTimeOver>
                <planningStatus>TARGET_TIME</planningStatus>
                <pointName>UNOKO</pointName>
                <pointUsage>COORDINATION</pointUsage>
                <advisoryInformation>
                    <speedAdvisory>MACH 0.82</speedAdvisory>
                </advisoryInformation>
            </meteringInformation>
            <flightIdentification>
                <arcid>KLM9164</arcid>
                <ades>LSZH</ades>
                <adep>EDDL</adep>
                <gufi codeSpace="urn:uuid"
                      creationTime="2026-04-08T15:33:00Z"
                      namespaceDomain="LOCATION_INDICATOR"
                      namespaceIdentifier="EDDL">8d34a7a0-be6c-421f-9820-b4979fbe8bb5</gufi>
            </flightIdentification>
        </arrivalManagementInformation>
        <arrivalManagementInformation>
            <amanTargetLandingTime>2026-04-08T20:13:00Z</amanTargetLandingTime>
            <arrivalManagementHandlingIndicator>HAS_LANDED</arrivalManagementHandlingIndicator>
            <lastFiledRecord>false</lastFiledRecord>
            <sequenceNumber>5</sequenceNumber>
            <typeOfAircraft>A319</typeOfAircraft>
            <wakeTurbulenceIcaoCategory>H</wakeTurbulenceIcaoCategory>
            <assignedArrivalRunway>03</assignedArrivalRunway>
            <meteringInformation>
                <amanTargetTimeOver>2026-04-08T19:49:00Z</amanTargetTimeOver>
                <planningStatus>CONTROLLED_TIME</planningStatus>
                <pointName>SUGOL</pointName>
                <pointUsage>FINAL_APPROACH_FIX</pointUsage>
            </meteringInformation>
            <flightIdentification>
                <arcid>TRA9892</arcid>
                <ades>LSZH</ades>
                <adep>ESSA</adep>
                <gufi codeSpace="urn:uuid"
                      creationTime="2026-04-08T09:33:00Z"
                      namespaceDomain="FULLY_QUALIFIED_DOMAIN_NAME"
                      namespaceIdentifier="provider.swim.aero">e70d23ab-c7ac-48ee-b049-ad36c7f6b8fe</gufi>
            </flightIdentification>
        </arrivalManagementInformation>
        <arrivalManagementInformation>
            <amanTargetLandingTime>2026-04-08T20:23:00Z</amanTargetLandingTime>
            <arrivalManagementHandlingIndicator>TIME_FROZEN</arrivalManagementHandlingIndicator>
            <lastFiledRecord>true</lastFiledRecord>
            <sequenceNumber>6</sequenceNumber>
            <typeOfAircraft>A388</typeOfAircraft>
            <wakeTurbulenceIcaoCategory>M</wakeTurbulenceIcaoCategory>
            <assignedArrivalRunway>27R</assignedArrivalRunway>
            <meteringInformation>
                <amanTargetTimeOver>2026-04-08T20:09:00Z</amanTargetTimeOver>
                <delayAtPoint>PT4M57S</delayAtPoint>
                <planningStatus>TARGET_TIME</planningStatus>
                <pointName>LURAC</pointName>
                <pointUsage>STACK_EXIT</pointUsage>
                <advisoryInformation>
                    <routeAdvisory>DIRECT MALOT</routeAdvisory>
                    <timeToGainOrLose>-95</timeToGainOrLose>
                </advisoryInformation>
            </meteringInformation>
            <flightIdentification>
                <arcid>DLH7726</arcid>
                <ades>LSZH</ades>
                <adep>EKCH</adep>
                <gufi codeSpace="urn:uuid"
                      creationTime="2026-04-08T17:33:00Z"
                      namespaceDomain="LOCATION_INDICATOR"
                      namespaceIdentifier="EKCH">a2f33592-0e75-4399-9df2-dba67bc456e4</gufi>
            </flightIdentification>
        </arrivalManagementInformation>
    </sequenceEntries>
</arrivalSequence>
