<?xml version="1.0" encoding="UTF-8"?>
<!-- This is FICTITIOUS TEST DATA generated for the SWIM Developer project.
     Data model based on EUROCAE ED-254 (Arrival Sequence Service Performance Standard)
     and FIXM 4.3 (Flight Information Exchange Model).
     All validation credits belong to their respective owners (EUROCAE, FIXM CCB, EUROCONTROL).

     THIS FICTITIOUS DATA SET IS PROVIDED "AS IS" AND ANY EXPRESS OR IMPLIED WARRANTIES,
     INCLUDING, BUT NOT LIMITED TO, THE IMPLIED WARRANTIES OF MERCHANTABILITY AND FITNESS
     FOR A PARTICULAR PURPOSE ARE DISCLAIMED.

     Created by Marcelo Sales (marcelo.d.sales@gmail.com) for the SWIM Developer project.
     Project: https://github.com/orgs/swim-developer/repositories
     Purpose: Testing and validation of SWIM Extended AMAN (E-AMAN) services.
     All credits to the original specification authors must be preserved. -->
<arrivalSequence xmlns="http://www.fixm.aero/ed254/1.0"
                 xmlns:fb="http://www.fixm.aero/base/4.3"
                 xmlns:fx="http://www.fixm.aero/flight/4.3">
    <creationTime>2026-04-08T06:32:00Z</creationTime>
    <publicationTime>2026-04-08T06:32:01.000Z</publicationTime>
    <firstMessageAfterServiceOutage>false</firstMessageAfterServiceOutage>
    <aerodromeDesignator>LEPA</aerodromeDesignator>
    <sequenceEntries>
        <arrivalManagementInformation>
            <amanTargetLandingTime>2026-04-08T06:56:00Z</amanTargetLandingTime>
            <arrivalManagementHandlingIndicator>SEQUENCED_STABLE</arrivalManagementHandlingIndicator>
            <lastFiledRecord>false</lastFiledRecord>
            <sequenceNumber>1</sequenceNumber>
            <typeOfAircraft>B738</typeOfAircraft>
            <wakeTurbulenceIcaoCategory>J</wakeTurbulenceIcaoCategory>
            <assignedArrivalRunway>32L</assignedArrivalRunway>
            <flightIdentification>
                <arcid>AUA1523</arcid>
                <ades>LEPA</ades>
                <adep>LPPT</adep>
                <gufi codeSpace="urn:uuid"
                      creationTime="2026-04-08T00:32:00Z"
                      namespaceDomain="FULLY_QUALIFIED_DOMAIN_NAME"
                      namespaceIdentifier="provider.swim.aero">602a1f37-63cc-4f58-a356-72e9d2c8a427</gufi>
            </flightIdentification>
            <totalDelay>
                <arrivalDelay>433</arrivalDelay>
            </totalDelay>
        </arrivalManagementInformation>
        <arrivalManagementInformation>
            <amanTargetLandingTime>2026-04-08T07:02:00Z</amanTargetLandingTime>
            <arrivalManagementHandlingIndicator>HAS_LANDED</arrivalManagementHandlingIndicator>
            <lastFiledRecord>false</lastFiledRecord>
            <sequenceNumber>2</sequenceNumber>
            <typeOfAircraft>A321</typeOfAircraft>
            <wakeTurbulenceIcaoCategory>M</wakeTurbulenceIcaoCategory>
            <assignedArrivalRunway>32L</assignedArrivalRunway>
            <meteringInformation>
                <amanTargetTimeOver>2026-04-08T06:38:00Z</amanTargetTimeOver>
                <planningStatus>ESTIMATED_TIME</planningStatus>
                <pointName>PINAR</pointName>
                <pointUsage>FINAL_APPROACH_FIX</pointUsage>
                <advisoryInformation>
                    <routeAdvisory>DIRECT AMRAM</routeAdvisory>
                    <speedAdvisory>MACH 0.73</speedAdvisory>
                    <timeToGainOrLose>71</timeToGainOrLose>
                </advisoryInformation>
            </meteringInformation>
            <flightIdentification>
                <arcid>SWR4178</arcid>
                <ades>LEPA</ades>
                <adep>EGKK</adep>
                <gufi codeSpace="urn:uuid"
                      creationTime="2026-04-08T04:32:00Z"
                      namespaceDomain="FULLY_QUALIFIED_DOMAIN_NAME"
                      namespaceIdentifier="provider.swim.aero">a887e869-d9e0-4262-a83a-7207e767d512</gufi>
            </flightIdentification>
        </arrivalManagementInformation>
        <arrivalManagementInformation>
            <amanTargetLandingTime>2026-04-08T07:04:00Z</amanTargetLandingTime>
            <arrivalManagementHandlingIndicator>MANUAL_INTERVENTION</arrivalManagementHandlingIndicator>
            <lastFiledRecord>false</lastFiledRecord>
            <sequenceNumber>3</sequenceNumber>
            <typeOfAircraft>A320</typeOfAircraft>
            <wakeTurbulenceIcaoCategory>H</wakeTurbulenceIcaoCategory>
            <assignedArrivalRunway>01L</assignedArrivalRunway>
            <meteringInformation>
                <amanTargetTimeOver>2026-04-08T06:54:00Z</amanTargetTimeOver>
                <delayAtPoint>PT5M29S</delayAtPoint>
                <planningStatus>TARGET_TIME</planningStatus>
                <pointName>PINAR</pointName>
                <pointUsage>STACK_EXIT</pointUsage>
                <advisoryInformation>
                    <routeAdvisory>DIRECT AMRAM</routeAdvisory>
                    <timeToGainOrLose>-4</timeToGainOrLose>
                </advisoryInformation>
            </meteringInformation>
            <flightIdentification>
                <arcid>TRA4223</arcid>
                <ades>LEPA</ades>
                <adep>LEMD</adep>
                <gufi codeSpace="urn:uuid"
                      creationTime="2026-04-07T22:32:00Z"
                      namespaceDomain="LOCATION_INDICATOR"
                      namespaceIdentifier="LEMD">b519c42f-8476-418f-a37b-3d8c8fe2a597</gufi>
            </flightIdentification>
        </arrivalManagementInformation>
        <arrivalManagementInformation>
            <amanTargetLandingTime>2026-04-08T07:16:00Z</amanTargetLandingTime>
            <arrivalManagementHandlingIndicator>SEQUENCED_FROZEN</arrivalManagementHandlingIndicator>
            <lastFiledRecord>false</lastFiledRecord>
            <sequenceNumber>4</sequenceNumber>
            <typeOfAircraft>E195</typeOfAircraft>
            <wakeTurbulenceIcaoCategory>M</wakeTurbulenceIcaoCategory>
            <assignedArrivalRunway>01R</assignedArrivalRunway>
            <meteringInformation>
                <amanTargetTimeOver>2026-04-08T07:04:00Z</amanTargetTimeOver>
                <delayAtPoint>PT6M25S</delayAtPoint>
                <planningStatus>CONTROLLED_TIME</planningStatus>
                <pointName>TOUKA</pointName>
                <pointUsage>INITIAL_APPROACH_FIX</pointUsage>
            </meteringInformation>
            <flightIdentification>
                <arcid>DLH3079</arcid>
                <ades>LEPA</ades>
                <adep>LFLL</adep>
                <gufi codeSpace="urn:uuid"
                      creationTime="2026-04-07T21:32:00Z"
                      namespaceDomain="FULLY_QUALIFIED_DOMAIN_NAME"
                      namespaceIdentifier="provider.swim.aero">dcafaef5-c353-4e0d-98f4-74df7e52105a</gufi>
            </flightIdentification>
            <totalDelay>
                <arrivalDelay>408</arrivalDelay>
            </totalDelay>
        </arrivalManagementInformation>
        <arrivalManagementInformation>
            <amanTargetLandingTime>2026-04-08T07:07:00Z</amanTargetLandingTime>
            <arrivalManagementHandlingIndicator>SEQUENCED_FROZEN</arrivalManagementHandlingIndicator>
            <lastFiledRecord>false</lastFiledRecord>
            <sequenceNumber>5</sequenceNumber>
            <typeOfAircraft>A320</typeOfAircraft>
            <wakeTurbulenceIcaoCategory>J</wakeTurbulenceIcaoCategory>
            <assignedArrivalRunway>32L</assignedArrivalRunway>
            <meteringInformation>
                <amanTargetTimeOver>2026-04-08T06:57:00Z</amanTargetTimeOver>
                <delayAtPoint>PT4M25S</delayAtPoint>
                <planningStatus>ESTIMATED_TIME</planningStatus>
                <pointName>BOMBI</pointName>
                <pointUsage>STACK_EXIT</pointUsage>
            </meteringInformation>
            <flightIdentification>
                <arcid>BAW6915</arcid>
                <ades>LEPA</ades>
                <adep>EDDM</adep>
                <gufi codeSpace="urn:uuid"
                      creationTime="2026-04-08T03:32:00Z"
                      namespaceDomain="LOCATION_INDICATOR"
                      namespaceIdentifier="EDDM">f602a0a5-3bdc-4af7-8ab0-c8ad982af45c</gufi>
            </flightIdentification>
        </arrivalManagementInformation>
        <arrivalManagementInformation>
            <amanTargetLandingTime>2026-04-08T07:22:00Z</amanTargetLandingTime>
            <arrivalManagementHandlingIndicator>IS_ON_FINAL</arrivalManagementHandlingIndicator>
            <lastFiledRecord>false</lastFiledRecord>
            <sequenceNumber>6</sequenceNumber>
            <typeOfAircraft>A388</typeOfAircraft>
            <wakeTurbulenceIcaoCategory>J</wakeTurbulenceIcaoCategory>
            <assignedArrivalRunway>25L</assignedArrivalRunway>
            <meteringInformation>
                <amanTargetTimeOver>2026-04-08T07:09:00Z</amanTargetTimeOver>
                <planningStatus>TARGET_TIME</planningStatus>
                <pointName>BOMBI</pointName>
                <pointUsage>FINAL_APPROACH_FIX</pointUsage>
                <advisoryInformation>
                    <routeAdvisory>DIRECT PINAR</routeAdvisory>
                </advisoryInformation>
            </meteringInformation>
            <flightIdentification>
                <arcid>KLM4405</arcid>
                <ades>LEPA</ades>
                <adep>LPPR</adep>
                <gufi codeSpace="urn:uuid"
                      creationTime="2026-04-07T23:32:00Z"
                      namespaceDomain="LOCATION_INDICATOR"
                      namespaceIdentifier="LPPR">480e1b69-b010-466a-8a99-c1e7c8d5f0e0</gufi>
            </flightIdentification>
        </arrivalManagementInformation>
        <arrivalManagementInformation>
            <amanTargetLandingTime>2026-04-08T07:34:00Z</amanTargetLandingTime>
            <arrivalManagementHandlingIndicator>SEQUENCED_FROZEN</arrivalManagementHandlingIndicator>
            <lastFiledRecord>true</lastFiledRecord>
            <sequenceNumber>7</sequenceNumber>
            <typeOfAircraft>B789</typeOfAircraft>
            <wakeTurbulenceIcaoCategory>H</wakeTurbulenceIcaoCategory>
            <assignedArrivalRunway>27L</assignedArrivalRunway>
            <meteringInformation>
                <amanTargetTimeOver>2026-04-08T07:12:00Z</amanTargetTimeOver>
                <delayAtPoint>PT6M50S</delayAtPoint>
                <planningStatus>ESTIMATED_TIME</planningStatus>
                <pointName>NUNOS</pointName>
                <pointUsage>INITIAL_APPROACH_FIX</pointUsage>
            </meteringInformation>
            <flightIdentification>
                <arcid>TRA4068</arcid>
                <ades>LEPA</ades>
                <adep>ENGM</adep>
                <gufi codeSpace="urn:uuid"
                      creationTime="2026-04-08T02:32:00Z"
                      namespaceDomain="FULLY_QUALIFIED_DOMAIN_NAME"
                      namespaceIdentifier="provider.swim.aero">1d86d9d3-fa0b-4ddf-9fc0-d78f867b8870</gufi>
            </flightIdentification>
        </arrivalManagementInformation>
    </sequenceEntries>
</arrivalSequence>
